{
  "type": "pfm:furniture",
  "ingredients": [
    {
      "item": "minecraft:light_blue_wool"
    },
    {
      "item": "minecraft:light_blue_wool"
    },
    {
      "item": "minecraft:light_blue_wool"
    },
    {
      "item": "betterend:end_lotus_stripped_log"
    },
    {
      "item": "betterend:end_lotus_stripped_log"
    }
  ],
  "result": {
    "item": "pfm:basic_lamp",
    "tag": {
      "BlockEntityTag": {
        "color": "light_blue",
        "variant": "betterend:end_lotus"
      }
    }
  }
}