{
  "type": "pfm:furniture",
  "group": "kitchen",
  "ingredients": [
    {
      "item": "luphieclutteredmod:luphie_purple_log"
    },
    {
      "item": "luphieclutteredmod:luphie_purple_log"
    },
    {
      "item": "luphieclutteredmod:luphie_purple_log"
    },
    {
      "item": "luphieclutteredmod:luphie_purple_log"
    },
    {
      "item": "luphieclutteredmod:luphie_purple_log"
    },
    {
      "item": "luphieclutteredmod:luphie_purple_planks"
    },
    {
      "item": "luphieclutteredmod:luphie_purple_planks"
    },
    {
      "item": "luphieclutteredmod:luphie_purple_planks"
    },
    {
      "item": "minecraft:furnace"
    }
  ],
  "result": {
    "item": "pfm:luphie_purple_luphieclutteredmod_kitchen_counter_oven"
  }
}