{
  "type": "pfm:furniture",
  "group": "kitchen",
  "ingredients": [
    {
      "item": "sakura:sakura_log"
    },
    {
      "item": "sakura:sakura_log"
    },
    {
      "item": "sakura:sakura_log"
    },
    {
      "item": "sakura:sakura_log"
    },
    {
      "item": "sakura:sakura_log"
    },
    {
      "item": "sakura:sakura_log"
    },
    {
      "item": "sakura:sakura_log"
    },
    {
      "item": "sakura:sakura_log"
    },
    {
      "item": "sakura:sakura_log"
    }
  ],
  "result": {
    "count": 6,
    "item": "pfm:sakura_sakura_kitchen_wall_counter"
  }
}